[
    { "Add": [1, 2] },
    { "Add": [1, 3] },
    { "Add": [1, 4] },
    { "Add": [1, 5] },
    { "Add": [1, 6] },
    { "Add": [1, 7] },
    { "Add": [1, 8] },
    { "Add": [1, 9] },
    { "Add": [1, 10] },
    { "Add": [1, 11] },
    { "Add": [1, 12] },
    { "Add": [1, 13] },
    { "Add": [1, 14] },
    { "Add": [1, 15] },
    { "Add": [1, 16] },
    { "Add": [1, 17] },
    { "Add": [1, 18] },
    { "Add": [1, 19] },
    { "Add": [1, 20] },
    { "Add": [1, 21] },
    { "Add": [1, 22] },
    { "Add": [1, 23] },
    { "Add": [1, 24] },
    { "Add": [1, 25] },
    { "Add": [1, 26] },
    { "Add": [1, 27] },
    { "Add": [1, 28] },
    { "Add": [1, 29] },
    { "Add": [1, 30] },
    { "Add": [1, 31] },
    { "Add": [1, 32] },
    { "Add": [1, 33] },
    { "Close": 1 },
    { "Add": [33, 34] },
    { "Close": 33 },
    { "Add": [34, 35] },
    { "Close": 34 },
    { "Add": [35, 36] },
    { "Close": 35 },
    { "Add": [36, 37] },
    { "Close": 36 },
    { "Add": [37, 38] },
    { "Close": 37 },
    { "Add": [38, 39] },
    { "Close": 38 },
    { "Add": [39, 40] },
    { "Close": 39 },
    { "Add": [40, 41] },
    { "Close": 40 },
    { "Add": [41, 42] },
    { "Close": 41 },
    { "Live": 42 },
    { "Close": 42 },
    { "Add": [32, 43] },
    { "Close": 32 },
    { "Add": [43, 44] },
    { "Close": 43 },
    { "Add": [44, 45] },
    { "Close": 44 },
    { "Add": [45, 46] },
    { "Close": 45 },
    { "Add": [46, 47] },
    { "Close": 46 },
    { "Add": [47, 48] },
    { "Close": 47 },
    { "Add": [48, 49] },
    { "Close": 48 },
    { "Add": [49, 41] },
    { "Close": 49 },
    { "Add": [31, 50] },
    { "Close": 31 },
    { "Add": [50, 51] },
    { "Close": 50 },
    { "Add": [51, 52] },
    { "Close": 51 },
    { "Add": [52, 10] },
    { "Close": 52 },
    { "Add": [30, 53] },
    { "Close": 30 },
    { "Add": [53, 54] },
    { "Close": 53 },
    { "Add": [54, 55] },
    { "Close": 54 },
    { "Add": [55, 9] },
    { "Close": 55 },
    { "Add": [29, 56] },
    { "Close": 29 },
    { "Add": [56, 57] },
    { "Close": 56 },
    { "Add": [57, 58] },
    { "Close": 57 },
    { "Add": [58, 8] },
    { "Close": 58 },
    { "Add": [28, 59] },
    { "Close": 28 },
    { "Add": [59, 60] },
    { "Close": 59 },
    { "Add": [60, 61] },
    { "Close": 60 },
    { "Add": [61, 7] },
    { "Close": 61 },
    { "Add": [27, 62] },
    { "Close": 27 },
    { "Add": [62, 63] },
    { "Close": 62 },
    { "Add": [63, 64] },
    { "Close": 63 },
    { "Add": [64, 6] },
    { "Close": 64 },
    { "Add": [26, 65] },
    { "Close": 26 },
    { "Add": [65, 66] },
    { "Close": 65 },
    { "Add": [66, 67] },
    { "Close": 66 },
    { "Add": [67, 5] },
    { "Close": 67 },
    { "Add": [25, 68] },
    { "Close": 25 },
    { "Add": [68, 69] },
    { "Close": 68 },
    { "Add": [69, 70] },
    { "Close": 69 },
    { "Add": [70, 4] },
    { "Close": 70 },
    { "Add": [24, 71] },
    { "Close": 24 },
    { "Add": [71, 72] },
    { "Close": 71 },
    { "Add": [72, 73] },
    { "Close": 72 },
    { "Add": [73, 3] },
    { "Close": 73 },
    { "Add": [23, 74] },
    { "Close": 23 },
    { "Add": [74, 75] },
    { "Close": 74 },
    { "Add": [75, 76] },
    { "Close": 75 },
    { "Add": [76, 77] },
    { "Close": 76 },
    { "Add": [77, 78] },
    { "Close": 77 },
    { "Add": [78, 79] },
    { "Close": 78 },
    { "Add": [79, 80] },
    { "Close": 79 },
    { "Add": [80, 41] },
    { "Close": 80 },
    { "Add": [22, 81] },
    { "Close": 22 },
    { "Add": [81, 82] },
    { "Close": 81 },
    { "Add": [82, 83] },
    { "Close": 82 },
    { "Add": [83, 84] },
    { "Close": 83 },
    { "Add": [84, 85] },
    { "Close": 84 },
    { "Add": [85, 86] },
    { "Close": 85 },
    { "Add": [86, 87] },
    { "Close": 86 },
    { "Add": [87, 88] },
    { "Close": 87 },
    { "Add": [88, 89] },
    { "Close": 88 },
    { "Add": [89, 41] },
    { "Close": 89 },
    { "Add": [21, 90] },
    { "Close": 21 },
    { "Add": [90, 91] },
    { "Close": 90 },
    { "Add": [91, 92] },
    { "Close": 91 },
    { "Add": [92, 93] },
    { "Close": 92 },
    { "Add": [93, 94] },
    { "Close": 93 },
    { "Add": [94, 95] },
    { "Close": 94 },
    { "Add": [95, 96] },
    { "Close": 95 },
    { "Add": [96, 97] },
    { "Close": 96 },
    { "Add": [97, 89] },
    { "Close": 97 },
    { "Add": [20, 98] },
    { "Close": 20 },
    { "Add": [98, 99] },
    { "Close": 98 },
    { "Add": [99, 100] },
    { "Close": 99 },
    { "Add": [100, 101] },
    { "Close": 100 },
    { "Add": [101, 78] },
    { "Close": 101 },
    { "Add": [19, 102] },
    { "Close": 19 },
    { "Add": [102, 103] },
    { "Close": 102 },
    { "Add": [103, 104] },
    { "Close": 103 },
    { "Add": [104, 105] },
    { "Close": 104 },
    { "Add": [105, 106] },
    { "Close": 105 },
    { "Add": [106, 107] },
    { "Close": 106 },
    { "Add": [107, 108] },
    { "Close": 107 },
    { "Add": [108, 109] },
    { "Close": 108 },
    { "Add": [109, 41] },
    { "Close": 109 },
    { "Add": [18, 110] },
    { "Close": 18 },
    { "Add": [110, 111] },
    { "Close": 110 },
    { "Add": [111, 112] },
    { "Close": 111 },
    { "Add": [112, 113] },
    { "Close": 112 },
    { "Add": [113, 85] },
    { "Close": 113 },
    { "Add": [17, 114] },
    { "Close": 17 },
    { "Add": [114, 115] },
    { "Close": 114 },
    { "Add": [115, 116] },
    { "Close": 115 },
    { "Add": [116, 117] },
    { "Close": 116 },
    { "Add": [117, 94] },
    { "Close": 117 },
    { "Add": [16, 118] },
    { "Close": 16 },
    { "Add": [118, 119] },
    { "Close": 118 },
    { "Add": [119, 120] },
    { "Close": 119 },
    { "Add": [120, 121] },
    { "Close": 120 },
    { "Add": [121, 122] },
    { "Close": 121 },
    { "Add": [122, 123] },
    { "Close": 122 },
    { "Add": [123, 124] },
    { "Close": 123 },
    { "Add": [124, 125] },
    { "Close": 124 },
    { "Add": [125, 126] },
    { "Close": 125 },
    { "Add": [126, 41] },
    { "Close": 126 },
    { "Add": [15, 127] },
    { "Close": 15 },
    { "Add": [127, 128] },
    { "Close": 127 },
    { "Add": [128, 129] },
    { "Close": 128 },
    { "Add": [129, 130] },
    { "Close": 129 },
    { "Add": [130, 131] },
    { "Close": 130 },
    { "Add": [131, 132] },
    { "Close": 131 },
    { "Add": [132, 133] },
    { "Close": 132 },
    { "Add": [133, 41] },
    { "Close": 133 },
    { "Add": [14, 134] },
    { "Close": 14 },
    { "Add": [134, 135] },
    { "Close": 134 },
    { "Add": [135, 136] },
    { "Close": 135 },
    { "Add": [136, 137] },
    { "Close": 136 },
    { "Add": [137, 138] },
    { "Close": 137 },
    { "Add": [138, 139] },
    { "Close": 138 },
    { "Add": [139, 40] },
    { "Close": 139 },
    { "Add": [13, 140] },
    { "Close": 13 },
    { "Add": [140, 141] },
    { "Close": 140 },
    { "Add": [141, 142] },
    { "Close": 141 },
    { "Add": [142, 143] },
    { "Close": 142 },
    { "Add": [143, 144] },
    { "Close": 143 },
    { "Add": [144, 145] },
    { "Close": 144 },
    { "Add": [145, 146] },
    { "Close": 145 },
    { "Add": [146, 80] },
    { "Close": 146 },
    { "Add": [12, 147] },
    { "Close": 12 },
    { "Add": [147, 148] },
    { "Close": 147 },
    { "Add": [148, 149] },
    { "Close": 148 },
    { "Add": [149, 2] },
    { "Close": 149 },
    { "Add": [11, 150] },
    { "Close": 11 },
    { "Add": [150, 151] },
    { "Close": 150 },
    { "Add": [151, 152] },
    { "Close": 151 },
    { "Add": [152, 153] },
    { "Close": 152 },
    { "Add": [153, 154] },
    { "Close": 153 },
    { "Add": [154, 155] },
    { "Close": 154 },
    { "Add": [155, 49] },
    { "Close": 155 },
    { "Add": [10, 156] },
    { "Close": 10 },
    { "Add": [156, 157] },
    { "Close": 156 },
    { "Add": [157, 158] },
    { "Close": 157 },
    { "Add": [158, 41] },
    { "Close": 158 },
    { "Add": [9, 159] },
    { "Close": 9 },
    { "Add": [159, 160] },
    { "Close": 159 },
    { "Add": [160, 161] },
    { "Close": 160 },
    { "Add": [161, 41] },
    { "Close": 161 },
    { "Add": [8, 162] },
    { "Close": 8 },
    { "Add": [162, 163] },
    { "Close": 162 },
    { "Add": [163, 164] },
    { "Close": 163 },
    { "Add": [164, 41] },
    { "Close": 164 },
    { "Add": [7, 165] },
    { "Close": 7 },
    { "Add": [165, 166] },
    { "Close": 165 },
    { "Add": [166, 167] },
    { "Close": 166 },
    { "Add": [167, 41] },
    { "Close": 167 },
    { "Add": [6, 168] },
    { "Close": 6 },
    { "Add": [168, 169] },
    { "Close": 168 },
    { "Add": [169, 164] },
    { "Close": 169 },
    { "Add": [5, 170] },
    { "Close": 5 },
    { "Add": [170, 171] },
    { "Close": 170 },
    { "Add": [171, 167] },
    { "Close": 171 },
    { "Add": [4, 172] },
    { "Close": 4 },
    { "Add": [172, 39] },
    { "Close": 172 },
    { "Add": [3, 173] },
    { "Close": 3 },
    { "Add": [173, 174] },
    { "Close": 173 },
    { "Add": [174, 175] },
    { "Close": 174 },
    { "Add": [175, 41] },
    { "Close": 175 },
    { "Add": [2, 176] },
    { "Close": 2 },
    { "Add": [176, 177] },
    { "Close": 176 },
    { "Add": [177, 133] },
    { "Close": 177 }
]
